{
    "specification": "probeinterface",
    "version": "0.3.2",
    "probes": [
        {
            "ndim": 2,
            "si_units": "um",
            "annotations": {
                "manufacturer": "cambridgeneurotech",
                "model_name": "ASSY-325-E-2"
            },
            "contact_annotations": {},
            "contact_positions": [
                [
                    70.0,
                    0.0
                ],
                [
                    70.0,
                    280.0
                ],
                [
                    0.0,
                    300.0
                ],
                [
                    70.0,
                    240.0
                ],
                [
                    0.0,
                    260.0
                ],
                [
                    70.0,
                    200.0
                ],
                [
                    0.0,
                    220.0
                ],
                [
                    70.0,
                    160.0
                ],
                [
                    0.0,
                    180.0
                ],
                [
                    70.0,
                    120.0
                ],
                [
                    0.0,
                    140.0
                ],
                [
                    70.0,
                    80.0
                ],
                [
                    0.0,
                    100.0
                ],
                [
                    70.0,
                    40.0
                ],
                [
                    0.0,
                    60.0
                ],
                [
                    0.0,
                    20.0
                ],
                [
                    320.0,
                    0.0
                ],
                [
                    320.0,
                    280.0
                ],
                [
                    250.0,
                    300.0
                ],
                [
                    320.0,
                    240.0
                ],
                [
                    250.0,
                    260.0
                ],
                [
                    320.0,
                    200.0
                ],
                [
                    250.0,
                    220.0
                ],
                [
                    320.0,
                    160.0
                ],
                [
                    250.0,
                    180.0
                ],
                [
                    320.0,
                    120.0
                ],
                [
                    250.0,
                    140.0
                ],
                [
                    320.0,
                    80.0
                ],
                [
                    250.0,
                    100.0
                ],
                [
                    320.0,
                    40.0
                ],
                [
                    250.0,
                    60.0
                ],
                [
                    250.0,
                    20.0
                ],
                [
                    500.0,
                    20.0
                ],
                [
                    500.0,
                    60.0
                ],
                [
                    570.0,
                    40.0
                ],
                [
                    500.0,
                    100.0
                ],
                [
                    570.0,
                    80.0
                ],
                [
                    500.0,
                    140.0
                ],
                [
                    570.0,
                    120.0
                ],
                [
                    500.0,
                    180.0
                ],
                [
                    570.0,
                    160.0
                ],
                [
                    500.0,
                    220.0
                ],
                [
                    570.0,
                    200.0
                ],
                [
                    500.0,
                    260.0
                ],
                [
                    570.0,
                    240.0
                ],
                [
                    500.0,
                    300.0
                ],
                [
                    570.0,
                    280.0
                ],
                [
                    570.0,
                    0.0
                ],
                [
                    750.0,
                    20.0
                ],
                [
                    750.0,
                    60.0
                ],
                [
                    820.0,
                    40.0
                ],
                [
                    750.0,
                    100.0
                ],
                [
                    820.0,
                    80.0
                ],
                [
                    750.0,
                    140.0
                ],
                [
                    820.0,
                    120.0
                ],
                [
                    750.0,
                    180.0
                ],
                [
                    820.0,
                    160.0
                ],
                [
                    750.0,
                    220.0
                ],
                [
                    820.0,
                    200.0
                ],
                [
                    750.0,
                    260.0
                ],
                [
                    820.0,
                    240.0
                ],
                [
                    750.0,
                    300.0
                ],
                [
                    820.0,
                    280.0
                ],
                [
                    820.0,
                    0.0
                ]
            ],
            "contact_plane_axes": [
                [
                    [
                        1.0,
                        0.0
                    ],
                    [
                        0.0,
                        1.0
                    ]
                ],
                [
                    [
                        1.0,
                        0.0
                    ],
                    [
                        0.0,
                        1.0
                    ]
                ],
                [
                    [
                        1.0,
                        0.0
                    ],
                    [
                        0.0,
                        1.0
                    ]
                ],
                [
                    [
                        1.0,
                        0.0
                    ],
                    [
                        0.0,
                        1.0
                    ]
                ],
                [
                    [
                        1.0,
                        0.0
                    ],
                    [
                        0.0,
                        1.0
                    ]
                ],
                [
                    [
                        1.0,
                        0.0
                    ],
                    [
                        0.0,
                        1.0
                    ]
                ],
                [
                    [
                        1.0,
                        0.0
                    ],
                    [
                        0.0,
                        1.0
                    ]
                ],
                [
                    [
                        1.0,
                        0.0
                    ],
                    [
                        0.0,
                        1.0
                    ]
                ],
                [
                    [
                        1.0,
                        0.0
                    ],
                    [
                        0.0,
                        1.0
                    ]
                ],
                [
                    [
                        1.0,
                        0.0
                    ],
                    [
                        0.0,
                        1.0
                    ]
                ],
                [
                    [
                        1.0,
                        0.0
                    ],
                    [
                        0.0,
                        1.0
                    ]
                ],
                [
                    [
                        1.0,
                        0.0
                    ],
                    [
                        0.0,
                        1.0
                    ]
                ],
                [
                    [
                        1.0,
                        0.0
                    ],
                    [
                        0.0,
                        1.0
                    ]
                ],
                [
                    [
                        1.0,
                        0.0
                    ],
                    [
                        0.0,
                        1.0
                    ]
                ],
                [
                    [
                        1.0,
                        0.0
                    ],
                    [
                        0.0,
                        1.0
                    ]
                ],
                [
                    [
                        1.0,
                        0.0
                    ],
                    [
                        0.0,
                        1.0
                    ]
                ],
                [
                    [
                        1.0,
                        0.0
                    ],
                    [
                        0.0,
                        1.0
                    ]
                ],
                [
                    [
                        1.0,
                        0.0
                    ],
                    [
                        0.0,
                        1.0
                    ]
                ],
                [
                    [
                        1.0,
                        0.0
                    ],
                    [
                        0.0,
                        1.0
                    ]
                ],
                [
                    [
                        1.0,
                        0.0
                    ],
                    [
                        0.0,
                        1.0
                    ]
                ],
                [
                    [
                        1.0,
                        0.0
                    ],
                    [
                        0.0,
                        1.0
                    ]
                ],
                [
                    [
                        1.0,
                        0.0
                    ],
                    [
                        0.0,
                        1.0
                    ]
                ],
                [
                    [
                        1.0,
                        0.0
                    ],
                    [
                        0.0,
                        1.0
                    ]
                ],
                [
                    [
                        1.0,
                        0.0
                    ],
                    [
                        0.0,
                        1.0
                    ]
                ],
                [
                    [
                        1.0,
                        0.0
                    ],
                    [
                        0.0,
                        1.0
                    ]
                ],
                [
                    [
                        1.0,
                        0.0
                    ],
                    [
                        0.0,
                        1.0
                    ]
                ],
                [
                    [
                        1.0,
                        0.0
                    ],
                    [
                        0.0,
                        1.0
                    ]
                ],
                [
                    [
                        1.0,
                        0.0
                    ],
                    [
                        0.0,
                        1.0
                    ]
                ],
                [
                    [
                        1.0,
                        0.0
                    ],
                    [
                        0.0,
                        1.0
                    ]
                ],
                [
                    [
                        1.0,
                        0.0
                    ],
                    [
                        0.0,
                        1.0
                    ]
                ],
                [
                    [
                        1.0,
                        0.0
                    ],
                    [
                        0.0,
                        1.0
                    ]
                ],
                [
                    [
                        1.0,
                        0.0
                    ],
                    [
                        0.0,
                        1.0
                    ]
                ],
                [
                    [
                        1.0,
                        0.0
                    ],
                    [
                        0.0,
                        1.0
                    ]
                ],
                [
                    [
                        1.0,
                        0.0
                    ],
                    [
                        0.0,
                        1.0
                    ]
                ],
                [
                    [
                        1.0,
                        0.0
                    ],
                    [
                        0.0,
                        1.0
                    ]
                ],
                [
                    [
                        1.0,
                        0.0
                    ],
                    [
                        0.0,
                        1.0
                    ]
                ],
                [
                    [
                        1.0,
                        0.0
                    ],
                    [
                        0.0,
                        1.0
                    ]
                ],
                [
                    [
                        1.0,
                        0.0
                    ],
                    [
                        0.0,
                        1.0
                    ]
                ],
                [
                    [
                        1.0,
                        0.0
                    ],
                    [
                        0.0,
                        1.0
                    ]
                ],
                [
                    [
                        1.0,
                        0.0
                    ],
                    [
                        0.0,
                        1.0
                    ]
                ],
                [
                    [
                        1.0,
                        0.0
                    ],
                    [
                        0.0,
                        1.0
                    ]
                ],
                [
                    [
                        1.0,
                        0.0
                    ],
                    [
                        0.0,
                        1.0
                    ]
                ],
                [
                    [
                        1.0,
                        0.0
                    ],
                    [
                        0.0,
                        1.0
                    ]
                ],
                [
                    [
                        1.0,
                        0.0
                    ],
                    [
                        0.0,
                        1.0
                    ]
                ],
                [
                    [
                        1.0,
                        0.0
                    ],
                    [
                        0.0,
                        1.0
                    ]
                ],
                [
                    [
                        1.0,
                        0.0
                    ],
                    [
                        0.0,
                        1.0
                    ]
                ],
                [
                    [
                        1.0,
                        0.0
                    ],
                    [
                        0.0,
                        1.0
                    ]
                ],
                [
                    [
                        1.0,
                        0.0
                    ],
                    [
                        0.0,
                        1.0
                    ]
                ],
                [
                    [
                        1.0,
                        0.0
                    ],
                    [
                        0.0,
                        1.0
                    ]
                ],
                [
                    [
                        1.0,
                        0.0
                    ],
                    [
                        0.0,
                        1.0
                    ]
                ],
                [
                    [
                        1.0,
                        0.0
                    ],
                    [
                        0.0,
                        1.0
                    ]
                ],
                [
                    [
                        1.0,
                        0.0
                    ],
                    [
                        0.0,
                        1.0
                    ]
                ],
                [
                    [
                        1.0,
                        0.0
                    ],
                    [
                        0.0,
                        1.0
                    ]
                ],
                [
                    [
                        1.0,
                        0.0
                    ],
                    [
                        0.0,
                        1.0
                    ]
                ],
                [
                    [
                        1.0,
                        0.0
                    ],
                    [
                        0.0,
                        1.0
                    ]
                ],
                [
                    [
                        1.0,
                        0.0
                    ],
                    [
                        0.0,
                        1.0
                    ]
                ],
                [
                    [
                        1.0,
                        0.0
                    ],
                    [
                        0.0,
                        1.0
                    ]
                ],
                [
                    [
                        1.0,
                        0.0
                    ],
                    [
                        0.0,
                        1.0
                    ]
                ],
                [
                    [
                        1.0,
                        0.0
                    ],
                    [
                        0.0,
                        1.0
                    ]
                ],
                [
                    [
                        1.0,
                        0.0
                    ],
                    [
                        0.0,
                        1.0
                    ]
                ],
                [
                    [
                        1.0,
                        0.0
                    ],
                    [
                        0.0,
                        1.0
                    ]
                ],
                [
                    [
                        1.0,
                        0.0
                    ],
                    [
                        0.0,
                        1.0
                    ]
                ],
                [
                    [
                        1.0,
                        0.0
                    ],
                    [
                        0.0,
                        1.0
                    ]
                ],
                [
                    [
                        1.0,
                        0.0
                    ],
                    [
                        0.0,
                        1.0
                    ]
                ]
            ],
            "contact_shapes": [
                "rect",
                "rect",
                "rect",
                "rect",
                "rect",
                "rect",
                "rect",
                "rect",
                "rect",
                "rect",
                "rect",
                "rect",
                "rect",
                "rect",
                "rect",
                "rect",
                "rect",
                "rect",
                "rect",
                "rect",
                "rect",
                "rect",
                "rect",
                "rect",
                "rect",
                "rect",
                "rect",
                "rect",
                "rect",
                "rect",
                "rect",
                "rect",
                "rect",
                "rect",
                "rect",
                "rect",
                "rect",
                "rect",
                "rect",
                "rect",
                "rect",
                "rect",
                "rect",
                "rect",
                "rect",
                "rect",
                "rect",
                "rect",
                "rect",
                "rect",
                "rect",
                "rect",
                "rect",
                "rect",
                "rect",
                "rect",
                "rect",
                "rect",
                "rect",
                "rect",
                "rect",
                "rect",
                "rect",
                "rect"
            ],
            "contact_shape_params": [
                {
                    "width": 11.0,
                    "height": 15.0
                },
                {
                    "width": 11.0,
                    "height": 15.0
                },
                {
                    "width": 11.0,
                    "height": 15.0
                },
                {
                    "width": 11.0,
                    "height": 15.0
                },
                {
                    "width": 11.0,
                    "height": 15.0
                },
                {
                    "width": 11.0,
                    "height": 15.0
                },
                {
                    "width": 11.0,
                    "height": 15.0
                },
                {
                    "width": 11.0,
                    "height": 15.0
                },
                {
                    "width": 11.0,
                    "height": 15.0
                },
                {
                    "width": 11.0,
                    "height": 15.0
                },
                {
                    "width": 11.0,
                    "height": 15.0
                },
                {
                    "width": 11.0,
                    "height": 15.0
                },
                {
                    "width": 11.0,
                    "height": 15.0
                },
                {
                    "width": 11.0,
                    "height": 15.0
                },
                {
                    "width": 11.0,
                    "height": 15.0
                },
                {
                    "width": 11.0,
                    "height": 15.0
                },
                {
                    "width": 11.0,
                    "height": 15.0
                },
                {
                    "width": 11.0,
                    "height": 15.0
                },
                {
                    "width": 11.0,
                    "height": 15.0
                },
                {
                    "width": 11.0,
                    "height": 15.0
                },
                {
                    "width": 11.0,
                    "height": 15.0
                },
                {
                    "width": 11.0,
                    "height": 15.0
                },
                {
                    "width": 11.0,
                    "height": 15.0
                },
                {
                    "width": 11.0,
                    "height": 15.0
                },
                {
                    "width": 11.0,
                    "height": 15.0
                },
                {
                    "width": 11.0,
                    "height": 15.0
                },
                {
                    "width": 11.0,
                    "height": 15.0
                },
                {
                    "width": 11.0,
                    "height": 15.0
                },
                {
                    "width": 11.0,
                    "height": 15.0
                },
                {
                    "width": 11.0,
                    "height": 15.0
                },
                {
                    "width": 11.0,
                    "height": 15.0
                },
                {
                    "width": 11.0,
                    "height": 15.0
                },
                {
                    "width": 11.0,
                    "height": 15.0
                },
                {
                    "width": 11.0,
                    "height": 15.0
                },
                {
                    "width": 11.0,
                    "height": 15.0
                },
                {
                    "width": 11.0,
                    "height": 15.0
                },
                {
                    "width": 11.0,
                    "height": 15.0
                },
                {
                    "width": 11.0,
                    "height": 15.0
                },
                {
                    "width": 11.0,
                    "height": 15.0
                },
                {
                    "width": 11.0,
                    "height": 15.0
                },
                {
                    "width": 11.0,
                    "height": 15.0
                },
                {
                    "width": 11.0,
                    "height": 15.0
                },
                {
                    "width": 11.0,
                    "height": 15.0
                },
                {
                    "width": 11.0,
                    "height": 15.0
                },
                {
                    "width": 11.0,
                    "height": 15.0
                },
                {
                    "width": 11.0,
                    "height": 15.0
                },
                {
                    "width": 11.0,
                    "height": 15.0
                },
                {
                    "width": 11.0,
                    "height": 15.0
                },
                {
                    "width": 11.0,
                    "height": 15.0
                },
                {
                    "width": 11.0,
                    "height": 15.0
                },
                {
                    "width": 11.0,
                    "height": 15.0
                },
                {
                    "width": 11.0,
                    "height": 15.0
                },
                {
                    "width": 11.0,
                    "height": 15.0
                },
                {
                    "width": 11.0,
                    "height": 15.0
                },
                {
                    "width": 11.0,
                    "height": 15.0
                },
                {
                    "width": 11.0,
                    "height": 15.0
                },
                {
                    "width": 11.0,
                    "height": 15.0
                },
                {
                    "width": 11.0,
                    "height": 15.0
                },
                {
                    "width": 11.0,
                    "height": 15.0
                },
                {
                    "width": 11.0,
                    "height": 15.0
                },
                {
                    "width": 11.0,
                    "height": 15.0
                },
                {
                    "width": 11.0,
                    "height": 15.0
                },
                {
                    "width": 11.0,
                    "height": 15.0
                },
                {
                    "width": 11.0,
                    "height": 15.0
                }
            ],
            "probe_planar_contour": [
                [
                    -7.5,
                    9000.0
                ],
                [
                    -7.5,
                    8800.0
                ],
                [
                    -7.5,
                    26.0
                ],
                [
                    35.0,
                    -24.0
                ],
                [
                    77.5,
                    26.0
                ],
                [
                    77.5,
                    8800.0
                ],
                [
                    242.5,
                    8800.0
                ],
                [
                    242.5,
                    26.0
                ],
                [
                    285.0,
                    -24.0
                ],
                [
                    327.5,
                    26.0
                ],
                [
                    327.5,
                    8800.0
                ],
                [
                    492.5,
                    8800.0
                ],
                [
                    492.5,
                    26.0
                ],
                [
                    535.0,
                    -24.0
                ],
                [
                    577.5,
                    26.0
                ],
                [
                    577.5,
                    8800.0
                ],
                [
                    742.5,
                    8800.0
                ],
                [
                    742.5,
                    26.0
                ],
                [
                    785.0,
                    -24.0
                ],
                [
                    827.5,
                    26.0
                ],
                [
                    827.5,
                    8800.0
                ],
                [
                    827.5,
                    9000.0
                ]
            ],
            "contact_ids": [
                "1",
                "2",
                "3",
                "4",
                "5",
                "6",
                "7",
                "8",
                "9",
                "10",
                "11",
                "12",
                "13",
                "14",
                "15",
                "16",
                "17",
                "18",
                "19",
                "20",
                "21",
                "22",
                "23",
                "24",
                "25",
                "26",
                "27",
                "28",
                "29",
                "30",
                "31",
                "32",
                "33",
                "34",
                "35",
                "36",
                "37",
                "38",
                "39",
                "40",
                "41",
                "42",
                "43",
                "44",
                "45",
                "46",
                "47",
                "48",
                "49",
                "50",
                "51",
                "52",
                "53",
                "54",
                "55",
                "56",
                "57",
                "58",
                "59",
                "60",
                "61",
                "62",
                "63",
                "64"
            ],
            "shank_ids": [
                "0",
                "0",
                "0",
                "0",
                "0",
                "0",
                "0",
                "0",
                "0",
                "0",
                "0",
                "0",
                "0",
                "0",
                "0",
                "0",
                "1",
                "1",
                "1",
                "1",
                "1",
                "1",
                "1",
                "1",
                "1",
                "1",
                "1",
                "1",
                "1",
                "1",
                "1",
                "1",
                "2",
                "2",
                "2",
                "2",
                "2",
                "2",
                "2",
                "2",
                "2",
                "2",
                "2",
                "2",
                "2",
                "2",
                "2",
                "2",
                "3",
                "3",
                "3",
                "3",
                "3",
                "3",
                "3",
                "3",
                "3",
                "3",
                "3",
                "3",
                "3",
                "3",
                "3",
                "3"
            ]
        }
    ]
}