{
    "specification": "probeinterface",
    "version": "0.2.24",
    "probes": [
        {
            "ndim": 2,
            "si_units": "um",
            "annotations": {
                "model_name": "ASSY-116-L2",
                "manufacturer": "cambridgeneurotech"
            },
            "contact_annotations": {},
            "contact_positions": [
                [
                    250.0,
                    550.0
                ],
                [
                    250.0,
                    300.0
                ],
                [
                    250.0,
                    750.0
                ],
                [
                    250.0,
                    650.0
                ],
                [
                    250.0,
                    700.0
                ],
                [
                    250.0,
                    0.0
                ],
                [
                    250.0,
                    100.0
                ],
                [
                    250.0,
                    50.0
                ],
                [
                    250.0,
                    150.0
                ],
                [
                    250.0,
                    600.0
                ],
                [
                    250.0,
                    500.0
                ],
                [
                    250.0,
                    200.0
                ],
                [
                    250.0,
                    400.0
                ],
                [
                    250.0,
                    250.0
                ],
                [
                    250.0,
                    450.0
                ],
                [
                    250.0,
                    350.0
                ],
                [
                    0.0,
                    450.0
                ],
                [
                    0.0,
                    350.0
                ],
                [
                    0.0,
                    400.0
                ],
                [
                    0.0,
                    250.0
                ],
                [
                    0.0,
                    500.0
                ],
                [
                    0.0,
                    200.0
                ],
                [
                    0.0,
                    150.0
                ],
                [
                    0.0,
                    600.0
                ],
                [
                    0.0,
                    100.0
                ],
                [
                    0.0,
                    50.0
                ],
                [
                    0.0,
                    700.0
                ],
                [
                    0.0,
                    0.0
                ],
                [
                    0.0,
                    750.0
                ],
                [
                    0.0,
                    650.0
                ],
                [
                    0.0,
                    550.0
                ],
                [
                    0.0,
                    300.0
                ]
            ],
            "contact_plane_axes": [
                [
                    [
                        1.0,
                        0.0
                    ],
                    [
                        0.0,
                        1.0
                    ]
                ],
                [
                    [
                        1.0,
                        0.0
                    ],
                    [
                        0.0,
                        1.0
                    ]
                ],
                [
                    [
                        1.0,
                        0.0
                    ],
                    [
                        0.0,
                        1.0
                    ]
                ],
                [
                    [
                        1.0,
                        0.0
                    ],
                    [
                        0.0,
                        1.0
                    ]
                ],
                [
                    [
                        1.0,
                        0.0
                    ],
                    [
                        0.0,
                        1.0
                    ]
                ],
                [
                    [
                        1.0,
                        0.0
                    ],
                    [
                        0.0,
                        1.0
                    ]
                ],
                [
                    [
                        1.0,
                        0.0
                    ],
                    [
                        0.0,
                        1.0
                    ]
                ],
                [
                    [
                        1.0,
                        0.0
                    ],
                    [
                        0.0,
                        1.0
                    ]
                ],
                [
                    [
                        1.0,
                        0.0
                    ],
                    [
                        0.0,
                        1.0
                    ]
                ],
                [
                    [
                        1.0,
                        0.0
                    ],
                    [
                        0.0,
                        1.0
                    ]
                ],
                [
                    [
                        1.0,
                        0.0
                    ],
                    [
                        0.0,
                        1.0
                    ]
                ],
                [
                    [
                        1.0,
                        0.0
                    ],
                    [
                        0.0,
                        1.0
                    ]
                ],
                [
                    [
                        1.0,
                        0.0
                    ],
                    [
                        0.0,
                        1.0
                    ]
                ],
                [
                    [
                        1.0,
                        0.0
                    ],
                    [
                        0.0,
                        1.0
                    ]
                ],
                [
                    [
                        1.0,
                        0.0
                    ],
                    [
                        0.0,
                        1.0
                    ]
                ],
                [
                    [
                        1.0,
                        0.0
                    ],
                    [
                        0.0,
                        1.0
                    ]
                ],
                [
                    [
                        1.0,
                        0.0
                    ],
                    [
                        0.0,
                        1.0
                    ]
                ],
                [
                    [
                        1.0,
                        0.0
                    ],
                    [
                        0.0,
                        1.0
                    ]
                ],
                [
                    [
                        1.0,
                        0.0
                    ],
                    [
                        0.0,
                        1.0
                    ]
                ],
                [
                    [
                        1.0,
                        0.0
                    ],
                    [
                        0.0,
                        1.0
                    ]
                ],
                [
                    [
                        1.0,
                        0.0
                    ],
                    [
                        0.0,
                        1.0
                    ]
                ],
                [
                    [
                        1.0,
                        0.0
                    ],
                    [
                        0.0,
                        1.0
                    ]
                ],
                [
                    [
                        1.0,
                        0.0
                    ],
                    [
                        0.0,
                        1.0
                    ]
                ],
                [
                    [
                        1.0,
                        0.0
                    ],
                    [
                        0.0,
                        1.0
                    ]
                ],
                [
                    [
                        1.0,
                        0.0
                    ],
                    [
                        0.0,
                        1.0
                    ]
                ],
                [
                    [
                        1.0,
                        0.0
                    ],
                    [
                        0.0,
                        1.0
                    ]
                ],
                [
                    [
                        1.0,
                        0.0
                    ],
                    [
                        0.0,
                        1.0
                    ]
                ],
                [
                    [
                        1.0,
                        0.0
                    ],
                    [
                        0.0,
                        1.0
                    ]
                ],
                [
                    [
                        1.0,
                        0.0
                    ],
                    [
                        0.0,
                        1.0
                    ]
                ],
                [
                    [
                        1.0,
                        0.0
                    ],
                    [
                        0.0,
                        1.0
                    ]
                ],
                [
                    [
                        1.0,
                        0.0
                    ],
                    [
                        0.0,
                        1.0
                    ]
                ],
                [
                    [
                        1.0,
                        0.0
                    ],
                    [
                        0.0,
                        1.0
                    ]
                ]
            ],
            "contact_shapes": [
                "rect",
                "rect",
                "rect",
                "rect",
                "rect",
                "rect",
                "rect",
                "rect",
                "rect",
                "rect",
                "rect",
                "rect",
                "rect",
                "rect",
                "rect",
                "rect",
                "rect",
                "rect",
                "rect",
                "rect",
                "rect",
                "rect",
                "rect",
                "rect",
                "rect",
                "rect",
                "rect",
                "rect",
                "rect",
                "rect",
                "rect",
                "rect"
            ],
            "contact_shape_params": [
                {
                    "width": 11,
                    "height": 15
                },
                {
                    "width": 11,
                    "height": 15
                },
                {
                    "width": 11,
                    "height": 15
                },
                {
                    "width": 11,
                    "height": 15
                },
                {
                    "width": 11,
                    "height": 15
                },
                {
                    "width": 11,
                    "height": 15
                },
                {
                    "width": 11,
                    "height": 15
                },
                {
                    "width": 11,
                    "height": 15
                },
                {
                    "width": 11,
                    "height": 15
                },
                {
                    "width": 11,
                    "height": 15
                },
                {
                    "width": 11,
                    "height": 15
                },
                {
                    "width": 11,
                    "height": 15
                },
                {
                    "width": 11,
                    "height": 15
                },
                {
                    "width": 11,
                    "height": 15
                },
                {
                    "width": 11,
                    "height": 15
                },
                {
                    "width": 11,
                    "height": 15
                },
                {
                    "width": 11,
                    "height": 15
                },
                {
                    "width": 11,
                    "height": 15
                },
                {
                    "width": 11,
                    "height": 15
                },
                {
                    "width": 11,
                    "height": 15
                },
                {
                    "width": 11,
                    "height": 15
                },
                {
                    "width": 11,
                    "height": 15
                },
                {
                    "width": 11,
                    "height": 15
                },
                {
                    "width": 11,
                    "height": 15
                },
                {
                    "width": 11,
                    "height": 15
                },
                {
                    "width": 11,
                    "height": 15
                },
                {
                    "width": 11,
                    "height": 15
                },
                {
                    "width": 11,
                    "height": 15
                },
                {
                    "width": 11,
                    "height": 15
                },
                {
                    "width": 11,
                    "height": 15
                },
                {
                    "width": 11,
                    "height": 15
                },
                {
                    "width": 11,
                    "height": 15
                }
            ],
            "probe_planar_contour": [
                [
                    -10.0,
                    840.0
                ],
                [
                    -10.0,
                    800.0
                ],
                [
                    -10.0,
                    -10.0
                ],
                [
                    11.0,
                    -28.0
                ],
                [
                    20.0,
                    -10.0
                ],
                [
                    56.5,
                    800.0
                ],
                [
                    240.0,
                    800.0
                ],
                [
                    240.0,
                    -10.0
                ],
                [
                    261.0,
                    -28.0
                ],
                [
                    270.0,
                    -10.0
                ],
                [
                    306.5,
                    800.0
                ],
                [
                    306.5,
                    840.0
                ]
            ],
            "contact_ids": [
                "1",
                "2",
                "3",
                "4",
                "5",
                "6",
                "7",
                "8",
                "9",
                "10",
                "11",
                "12",
                "13",
                "14",
                "15",
                "16",
                "17",
                "18",
                "19",
                "20",
                "21",
                "22",
                "23",
                "24",
                "25",
                "26",
                "27",
                "28",
                "29",
                "30",
                "31",
                "32"
            ],
            "shank_ids": [
                "1",
                "1",
                "1",
                "1",
                "1",
                "1",
                "1",
                "1",
                "1",
                "1",
                "1",
                "1",
                "1",
                "1",
                "1",
                "1",
                "0",
                "0",
                "0",
                "0",
                "0",
                "0",
                "0",
                "0",
                "0",
                "0",
                "0",
                "0",
                "0",
                "0",
                "0",
                "0"
            ]
        }
    ]
}